MANIFEST.in
README.rst
setup.cfg
setup.py
mementor/__init__.py
mementor/image_crop.py
mementor/image_join.py
mementor/image_make.py
mementor/image_ocr.py
mementor/memento.py
mementor/memento_all.py
mementor/ocr_orientation.py
mementor/ocr_rename.py
mementor/ocr_save.py
mementor.egg-info/PKG-INFO
mementor.egg-info/SOURCES.txt
mementor.egg-info/dependency_links.txt
mementor.egg-info/entry_points.txt
mementor.egg-info/not-zip-safe
mementor.egg-info/requires.txt
mementor.egg-info/top_level.txt