Metadata-Version: 1.0
Name: mementor
Version: 1.0.4
Summary: A library to fetch images from directory to fix orientation and pull OCR from the images along with editing the text inside images, primarily focusing on memes
Home-page: https://github.com/aryaminus/memento
Author: Sunim Acharya
Author-email: sunim.54@gmail.com
License: UNKNOWN
Keywords: ocr,image,opencv,tesseract,orientation
Platform: UNKNOWN
